sc2/__init__.py
sc2/fingerprint.py
sc2/export/__init__.py
sc2/export/drawio_exporter.py
sc2/export/graphml_exporter.py
sc2/scng/__init__.py
sc2/scng/audit/__init__.py
sc2/scng/audit/__main__.py
sc2/scng/audit/cli.py
sc2/scng/audit/collector.py
sc2/scng/audit/report.py
sc2/scng/creds/__init__.py
sc2/scng/creds/__main__.py
sc2/scng/creds/cli.py
sc2/scng/creds/encryption.py
sc2/scng/creds/models.py
sc2/scng/creds/resolver.py
sc2/scng/creds/schema.py
sc2/scng/creds/vault.py
sc2/scng/discovery/__init__.py
sc2/scng/discovery/__main__.py
sc2/scng/discovery/cli.py
sc2/scng/discovery/discovery_controller.py
sc2/scng/discovery/discovery_to_map.py
sc2/scng/discovery/engine.py
sc2/scng/discovery/events.py
sc2/scng/discovery/models.py
sc2/scng/discovery/oids.py
sc2/scng/discovery/snmp/__init__.py
sc2/scng/discovery/snmp/parsers.py
sc2/scng/discovery/snmp/walker.py
sc2/scng/discovery/snmp/collectors/__init__.py
sc2/scng/discovery/snmp/collectors/arp.py
sc2/scng/discovery/snmp/collectors/cdp.py
sc2/scng/discovery/snmp/collectors/interfaces.py
sc2/scng/discovery/snmp/collectors/lldp.py
sc2/scng/discovery/snmp/collectors/system.py
sc2/scng/discovery/ssh/__init__.py
sc2/scng/discovery/ssh/__main__.py
sc2/scng/discovery/ssh/client.py
sc2/scng/discovery/ssh/collector.py
sc2/scng/discovery/ssh/parsers.py
sc2/scng/utils/__init__.py
sc2/scng/utils/resource_helper.py
sc2/scng/utils/tfsm_engine.py
sc2/scng/utils/tfsm_fire.py
sc2/scng/utils/tfsm_fire_tester.py
sc2/scng/utils/tfsm_templates.db
sc2/ui/__init__.py
sc2/ui/__main__.py
sc2/ui/help_dialog.py
sc2/ui/login.py
sc2/ui/main_window.py
sc2/ui/security_integration.py
sc2/ui/settings.py
sc2/ui/themes.py
sc2/ui/assets/banner_amber.png
sc2/ui/assets/banner_cyber.png
sc2/ui/assets/banner_light.png
sc2/ui/assets/icons_lib/100baset-hub.svg
sc2/ui/assets/icons_lib/100baset_hub.jpg
sc2/ui/assets/icons_lib/10700.jpg
sc2/ui/assets/icons_lib/10700.svg
sc2/ui/assets/icons_lib/10GE_FCoE.jpg
sc2/ui/assets/icons_lib/10ge-fcoe.svg
secure_cartography-2.0.14.dist-info/METADATA
secure_cartography-2.0.14.dist-info/WHEEL
secure_cartography-2.0.14.dist-info/entry_points.txt
secure_cartography-2.0.14.dist-info/top_level.txt
secure_cartography-2.0.14.dist-info/RECORD
