Metadata-Version: 2.4
Name: secure-cartography
Version: 2.0.14
Summary: SSH & SNMP-Based Network Discovery and Topology Mapping
Home-page: https://github.com/scottpeterman/secure_cartography
Author: Scott Peterman
Author-email: scottpeterman@gmail.com
License: GPL-3.0
Project-URL: Bug Reports, https://github.com/scottpeterman/secure_cartography/issues
Project-URL: Source, https://github.com/scottpeterman/secure_cartography
Project-URL: Documentation, https://github.com/scottpeterman/secure_cartography#readme
Keywords: network,discovery,topology,snmp,ssh,cdp,lldp,cisco,arista,juniper,network-automation,network-mapping
Classifier: Development Status :: 4 - Beta
Classifier: Environment :: X11 Applications :: Qt
Classifier: Environment :: Win32 (MS Windows)
Classifier: Environment :: MacOS X
Classifier: Intended Audience :: System Administrators
Classifier: Intended Audience :: Information Technology
Classifier: Intended Audience :: Telecommunications Industry
Classifier: License :: OSI Approved :: GNU General Public License v3 (GPLv3)
Classifier: Operating System :: OS Independent
Classifier: Programming Language :: Python :: 3
Classifier: Programming Language :: Python :: 3.10
Classifier: Programming Language :: Python :: 3.11
Classifier: Programming Language :: Python :: 3.12
Classifier: Topic :: System :: Networking
Classifier: Topic :: System :: Networking :: Monitoring
Classifier: Topic :: System :: Systems Administration
Requires-Python: >=3.9
Requires-Dist: pysnmp>=7.1
Requires-Dist: paramiko>=3.0
Requires-Dist: textfsm>=1.1
Requires-Dist: cryptography>=42.0
Requires-Dist: PyQt6>=6.6
Requires-Dist: PyQt6-WebEngine>=6.6
Requires-Dist: fastapi>=0.100
Requires-Dist: uvicorn>=0.27
Requires-Dist: pydantic>=2.0
Requires-Dist: aiofiles>=23.0
Requires-Dist: PyYAML>=6.0
Requires-Dist: click>=8.0
Requires-Dist: requests>=2.30
Requires-Dist: openpyxl>=3.1
Requires-Dist: python-dotenv>=1.0
Provides-Extra: dev
Requires-Dist: pytest>=7.0; extra == "dev"
Requires-Dist: pytest-asyncio>=0.21; extra == "dev"
Requires-Dist: black>=23.0; extra == "dev"
Requires-Dist: ruff>=0.1; extra == "dev"
Dynamic: author
Dynamic: author-email
Dynamic: classifier
Dynamic: description
Dynamic: description-content-type
Dynamic: home-page
Dynamic: keywords
Dynamic: license
Dynamic: project-url
Dynamic: provides-extra
Dynamic: requires-dist
Dynamic: requires-python
Dynamic: summary
